investate/__init__.py
investate-0.0.5.dist-info/LICENSE
investate-0.0.5.dist-info/METADATA
investate-0.0.5.dist-info/WHEEL
investate-0.0.5.dist-info/top_level.txt
investate-0.0.5.dist-info/RECORD
